OSL_CGCD/__init__.py
OSL_CGCD/modulo.py
osl_cgcd-0.1.5.dist-info/METADATA
osl_cgcd-0.1.5.dist-info/WHEEL
osl_cgcd-0.1.5.dist-info/top_level.txt
osl_cgcd-0.1.5.dist-info/RECORD
