Metadata-Version: 2.4
Name: OSL_CGCD
Version: 0.1.5
Summary: programa para la deconvolución de curvas OSL utilizando el método CGCD
Home-page: https://pypi.org/project/OSL_CGCD/
Author: EDWIN JOEL PILCO QUISPE
Author-email: edwinpilco10@gmail.com
Classifier: Programming Language :: Python :: 3
Classifier: License :: OSI Approved :: MIT License
Classifier: Operating System :: OS Independent
Classifier: Intended Audience :: Science/Research
Classifier: Topic :: Scientific/Engineering
Requires-Python: >=3.6
Dynamic: author
Dynamic: author-email
Dynamic: classifier
Dynamic: description
Dynamic: description-content-type
Dynamic: home-page
Dynamic: requires-python
Dynamic: summary
